setup.cfg
setup.py
schema_transformer/__init__.py
schema_transformer/helpers.py
schema_transformer/transformer.py
schema_transformer.egg-info/PKG-INFO
schema_transformer.egg-info/SOURCES.txt
schema_transformer.egg-info/dependency_links.txt
schema_transformer.egg-info/requires.txt
schema_transformer.egg-info/top_level.txt