Metadata-Version: 1.1
Name: schema-transformer
Version: 0.0.2
Summary: A library for doing schema transformations
Home-page: https://github.com/fabianvf/schema-transformer
Author: Fabian von Feilitzsch
Author-email: fabian@cos.io
License: UNKNOWN
Download-URL: https://github.com/fabianvf/schema-transformer/tarball/0.0.2
Platform: UNKNOWN
